{
    "Ar36": {
        "error": 0.0002661281695885139,
        "error_type": "SEM",
        "filter_outliers_dict": {
            "filter_outliers": false,
            "iterations": 1,
            "std_devs": 2,
            "use_iqr_filtering": false,
            "use_standard_deviation_filtering": false
        },
        "fit": "Linear",
        "fn": 150,
        "include_baseline_error": false,
        "n": 150,
        "outlier_excluded": [],
        "reviewed": true,
        "user_excluded": [],
        "value": 0.011758973917711855
    },
    "Ar37": {
        "error": 0.00925254846056128,
        "error_type": "SEM",
        "filter_outliers_dict": {
            "filter_outliers": true,
            "iterations": 1,
            "std_devs": 2
        },
        "fit": "Linear",
        "value": -0.009694277674611295
    },
    "Ar38": {
        "error": 0.012178120971128508,
        "error_type": "SEM",
        "filter_outliers_dict": {
            "filter_outliers": false,
            "iterations": 0,
            "std_devs": 0,
            "use_iqr_filtering": false,
            "use_standard_deviation_filtering": false
        },
        "fit": "Linear",
        "fn": 150,
        "include_baseline_error": false,
        "n": 150,
        "outlier_excluded": [],
        "reviewed": true,
        "user_excluded": [],
        "value": 0.05935137256163986
    },
    "Ar39": {
        "error": 0.010457805740786408,
        "error_type": "SEM",
        "filter_outliers_dict": {
            "filter_outliers": false,
            "iterations": 0,
            "std_devs": 0,
            "use_iqr_filtering": false,
            "use_standard_deviation_filtering": false
        },
        "fit": "Linear",
        "fn": 150,
        "include_baseline_error": false,
        "n": 150,
        "outlier_excluded": [],
        "reviewed": true,
        "user_excluded": [],
        "value": 4.99278335734482
    },
    "Ar40": {
        "error": 0.03423555947760138,
        "error_type": "SEM",
        "filter_outliers_dict": {
            "filter_outliers": false,
            "iterations": 0,
            "std_devs": 0,
            "use_iqr_filtering": false,
            "use_standard_deviation_filtering": false
        },
        "fit": "Linear",
        "fn": 150,
        "include_baseline_error": false,
        "n": 150,
        "outlier_excluded": [],
        "reviewed": true,
        "user_excluded": [],
        "value": 85.56992915346342
    }
}